_cli.py
brainmeshing/__init__.py
brainmeshing/_cli.py
brainmeshing/boundary_cell_refinement.py
brainmeshing/mesh_generation.py
brainmeshing/utils.py
brainmeshing/ventricles.py
brainmeshing/white_gray_separation.py
dti/__init__.py
dti/_cli.py
dti/clean_dti_data.py
dti/dtifit.py
dti/eddy.py
dti/reslice_dti.py
dti/topup.py
dti/utils.py
gmri2fem/__init__.py
gmri2fem/_cli.py
gmri2fem/concentration.py
gmri2fem/csf_segmentation.py
gmri2fem/hybrid_t1map.py
gmri2fem/ll_dicom.py
gmri2fem/looklocker_t1map.py
gmri2fem/masking.py
gmri2fem/mixed_curve_fit.py
gmri2fem/mixed_dicom.py
gmri2fem/mixed_t1map.py
gmri2fem/orbital_refroi.py
gmri2fem/plotting.py
gmri2fem/regionwise_statistics.py
gmri2fem/reslice_4d.py
gmri2fem/segment_tools.py
gmri2fem/segmentation_groups.py
gmri2fem/segmentation_refinement.py
gmri2fem/t1_weighted.py
gmri2fem/t1maps.py
gmri2fem/utils.py
gmri2fem/visualization.py
gmri2fem-0.2.8.dist-info/licenses/LICENSE
i2m/__init__.py
i2m/_cli.py
i2m/collect_mesh_data.py
i2m/concentrations_to_mesh.py
i2m/dti_data_to_mesh.py
i2m/mesh_segments.py
i2m/mri2fenics.py
i2m/vtk2mri.py
i2m/vtk_converter.py
gmri2fem-0.2.8.dist-info/METADATA
gmri2fem-0.2.8.dist-info/WHEEL
gmri2fem-0.2.8.dist-info/entry_points.txt
gmri2fem-0.2.8.dist-info/top_level.txt
gmri2fem-0.2.8.dist-info/RECORD
