Metadata-Version: 2.4
Name: gmri2fem
Version: 0.2.8
Summary: Processing pipeline for glymphatic MRI.
Author-email: Jørgen Riseth <jnriseth@gmail.com>
License-Expression: MIT
Project-URL: Homepage, https://github.com/jorgenriseth/gMRI2FEM.git
Requires-Python: <3.13,>=3.11
License-File: LICENSE
Requires-Dist: loguru
Requires-Dist: matplotlib
Requires-Dist: meshio
Requires-Dist: nibabel
Requires-Dist: numpy
Requires-Dist: pint
Requires-Dist: pydicom
Requires-Dist: pymeshfix
Requires-Dist: scikit-image
Requires-Dist: scipy
Requires-Dist: tqdm
Requires-Dist: simple-mri>=0.1.6
Requires-Dist: panta-rhei>=0.7.0
Requires-Dist: click
Requires-Dist: vtk
Requires-Dist: pyvista[all]
Dynamic: license-file
